vsco/__init__.py
vsco/exceptions.py
vsco/vsco.py
vsco-0.0.5.dist-info/METADATA
vsco-0.0.5.dist-info/WHEEL
vsco-0.0.5.dist-info/top_level.txt
vsco-0.0.5.dist-info/RECORD
