Metadata-Version: 2.1
Name: vsco
Version: 0.0.5
Summary: A Python API wrapper for VSCO.
Home-page: https://github.com/quintindunn/vsco.py
Author: Quintin Dunn
Author-email: dunnquintin07@gmail.com
Keywords: social media,vsco,api,api wrapper
Classifier: Development Status :: 5 - Production/Stable
Classifier: Operating System :: Microsoft :: Windows :: Windows 10
Classifier: Programming Language :: Python :: 3
Requires-Dist: pillow
Requires-Dist: requests
